MANIFEST.in
README.rst
gg_scraper.py
setup.py
gg_scraper.egg-info/PKG-INFO
gg_scraper.egg-info/SOURCES.txt
gg_scraper.egg-info/dependency_links.txt
gg_scraper.egg-info/top_level.txt
test/__init__.py
test/__init__.pyc
test/group.html
test/group.yaml
test/mangled_address.cnf
test/mbox.mbx
test/mbox_unmangled.mbx
test/message.eml
test/py26_unicode.eml
test/test_functional.py
test/test_functional.pyc
test/test_unit.py
test/test_unit.pyc
test/unmangled_address.cnf