Metadata-Version: 1.1
Name: gg-scraper
Version: 0.10.0
Summary: Download a Google Group to MBOX
Home-page: https://gitlab.com/mcepl/gg_scraper
Author: Matěj Cepl
Author-email: mcepl@cepl.eu
License: GNU GPL
Keywords: email,Google Groups,scrap,backup
Platform: UNKNOWN
Classifier: Development Status :: 3 - Alpha
Classifier: Operating System :: OS Independent
Classifier: Intended Audience :: Information Technology
Classifier: License :: OSI Approved :: GNU General Public License v3 (GPLv3)
Classifier: Natural Language :: English
Classifier: Programming Language :: Python :: 2
Classifier: Programming Language :: Python :: 3
Classifier: Topic :: Communications :: Email
Classifier: Topic :: Communications :: Conferencing
Requires: beautifulsoup4
Requires: PyYAML
